api5simbiz/__init__.py
api5simbiz/main.py
api5simbiz-1.0.0.dist-info/METADATA
api5simbiz-1.0.0.dist-info/WHEEL
api5simbiz-1.0.0.dist-info/top_level.txt
api5simbiz-1.0.0.dist-info/RECORD
