Metadata-Version: 2.1
Name: api5simbiz
Version: 1.0.0
Summary: Упрощенное взаимодействие с API веб-сайта 5sim.biz
Home-page: https://github.com/Gitrer/Fivesimapi
Author: Sierro
Author-email: himan.youtube@mail.ru
Project-URL: Documentation, https://5sim.biz/docs
Keywords: example python
Classifier: License :: OSI Approved :: MIT License
Classifier: Operating System :: OS Independent
Requires-Python: >=3.7
Requires-Dist: requests
